MANIFEST.in
README.html
README.rst
setup.py
TGFirebugLite.egg-info/PKG-INFO
TGFirebugLite.egg-info/SOURCES.txt
TGFirebugLite.egg-info/dependency_links.txt
TGFirebugLite.egg-info/entry_points.txt
TGFirebugLite.egg-info/not-zip-safe
TGFirebugLite.egg-info/paster_plugins.txt
TGFirebugLite.egg-info/requires.txt
TGFirebugLite.egg-info/sqlobject.txt
TGFirebugLite.egg-info/top_level.txt
firebug/__init__.py
firebug/release.py
firebug/widgets.py
