Metadata-Version: 1.0
Name: TGFirebugLite
Version: 1.0b
Summary: A TurboGears widgets wrapper for the Firebug Lite JavaScript Library.
Home-page: http://chrisarndt.de/projects/tgfirebuglite/
Author: Christopher Arndt
Author-email: chris@chrisarndt.de
License: MPL/GPL/LGPL
Download-URL: http://chrisarndt.de/projects/tgfirebuglite/download/TGFirebugLite-1.0b-py2.4.egg
Keywords: turbogears.widgets
Platform: UNKNOWN
Classifier: Development Status :: 4 - Beta
Classifier: Environment :: Web Environment
Classifier: Framework :: TurboGears
Classifier: Framework :: TurboGears :: Widgets
Classifier: Intended Audience :: Developers
Classifier: License :: OSI Approved :: Mozilla Public License 1.1 (MPL 1.1)
Classifier: License :: OSI Approved :: GNU General Public License (GPL)
Classifier: License :: OSI Approved :: GNU Library or Lesser General Public License (LGPL)
Classifier: Operating System :: OS Independent
Classifier: Programming Language :: Python
Classifier: Programming Language :: JavaScript
Classifier: Topic :: Software Development :: Testing
Classifier: Topic :: Software Development :: Debuggers
